COPYRIGHT
MANIFEST.in
Makefile
README
setup.py
test/__init__.py
test/__init__.pyc
test/test_compile.py
test/__pycache__/test_compile.cpython-27-PYTEST.pyc
tiddlywebplugins/__init__.py
tiddlywebplugins/openid2.py
tiddlywebplugins.openid2.egg-info/PKG-INFO
tiddlywebplugins.openid2.egg-info/SOURCES.txt
tiddlywebplugins.openid2.egg-info/dependency_links.txt
tiddlywebplugins.openid2.egg-info/namespace_packages.txt
tiddlywebplugins.openid2.egg-info/not-zip-safe
tiddlywebplugins.openid2.egg-info/requires.txt
tiddlywebplugins.openid2.egg-info/top_level.txt