Metadata-Version: 1.0
Name: tiddlywebplugins.openid2
Version: 0.8
Summary: An improved openid challenger for TiddlyWeb
Home-page: http://pypi.python.org/pypi/tiddlywebplugins.openid2
Author: Chris Dent
Author-email: cdent@peermore.com
License: BSD
Platform: Posix; MacOS X; Windows
